DSMD/__init__.py
DSMD/main.py
DSMD-0.0.3.dist-info/LICENSE 
DSMD-0.0.3.dist-info/METADATA
DSMD-0.0.3.dist-info/WHEEL
DSMD-0.0.3.dist-info/top_level.txt
DSMD-0.0.3.dist-info/zip-safe
DSMD-0.0.3.dist-info/RECORD
