Metadata-Version: 2.1
Name: DSMD
Version: 0.0.3
Summary: Markup lang
Home-page: UNKNOWN
Author: darkdarcool30
Author-email: darkdarcool@gmail.com
License: GNU General Public License v3 (GPLv3)
Platform: UNKNOWN
Classifier: Programming Language :: Python :: 3
Classifier: License :: OSI Approved :: GNU General Public License v3 (GPLv3)
Classifier: Operating System :: OS Independent
Requires-Python: >=3.0
